setup.py
distributions/Binomialdistribution.py
distributions/Gaussiandistribution.py
distributions/Generaldistribution.py
distributions/__init__.py
lite_distributions.egg-info/PKG-INFO
lite_distributions.egg-info/SOURCES.txt
lite_distributions.egg-info/dependency_links.txt
lite_distributions.egg-info/not-zip-safe
lite_distributions.egg-info/top_level.txt